PxxDataCollection/__init__.py
PxxDataCollection/_login.py
PxxDataCollection/_types.py
PxxDataCollection/_utils.py
PxxDataCollection/collector.py
PxxDataCollection/marketing/_dict.py
PxxDataCollection/marketing/_utils.py
PxxDataCollection/marketing/account.py
PxxDataCollection/marketing/marketing.py
PxxDataCollection/marketing/report.py
PxxDataCollection/mms/_dict.py
PxxDataCollection/mms/_utils.py
PxxDataCollection/mms/customer_service.py
PxxDataCollection/mms/data_center.py
PxxDataCollection/mms/mms.py
pxx_data_collection-1.0.16.dist-info/LICENSE
pxx_data_collection-1.0.16.dist-info/METADATA
pxx_data_collection-1.0.16.dist-info/WHEEL
pxx_data_collection-1.0.16.dist-info/RECORD
