Metadata-Version: 2.3
Name: pxx-data-collection
Version: 1.0.16
Summary: PXX Background data collection
License: MIT
Author: martianbugs
Requires-Python: >=3.9
Classifier: License :: OSI Approved :: MIT License
Classifier: Programming Language :: Python :: 3
Classifier: Programming Language :: Python :: 3.9
Classifier: Programming Language :: Python :: 3.10
Classifier: Programming Language :: Python :: 3.11
Classifier: Programming Language :: Python :: 3.12
Classifier: Programming Language :: Python :: 3.13
Requires-Dist: drissionpage (>=4.1.0.17,<5.0.0.0)
Requires-Dist: pxx-font-decrypt (>=1.0.0,<2.0.0)
